MANIFEST.in
README.rst
setup.py
txghserf/__init__.py
txghserf/cidr.py
txghserf/server.py
txghserf.egg-info/PKG-INFO
txghserf.egg-info/SOURCES.txt
txghserf.egg-info/dependency_links.txt
txghserf.egg-info/requires.txt
txghserf.egg-info/top_level.txt
txghserf/static/index.html
txghserf/static/js/app.js
txghserf/static/lib/ui-bootstrap-tpls-0.1.0-SNAPSHOT.min.js
txghserf/static/lib/utils.js
txghserf/static/partials/hook.html
txghserf/static/partials/login.html
txghserf/static/partials/organization.html
txghserf/static/partials/organizations.html
txghserf/static/partials/repository.html
txghserf/tests/__init__.py
txghserf/tests/test_server.py