Metadata-Version: 1.1
Name: txghserf
Version: 0.3.0
Summary: Simple server to listen for GitHub repo hooks.
Home-page: https://github.com/chevah/txghserf
Author: Adi Roiban
Author-email: adi.roiban@chevah.com
License: BSD 3-Clause
Platform: any
Classifier: Development Status :: 4 - Beta
Classifier: Intended Audience :: Developers
Classifier: Programming Language :: Python
